MANIFEST.in
README.rst
setup.cfg
setup.py
bootstrap_components/__init__.py
bootstrap_components/apps.py
bootstrap_components/migrations/__init__.py
bootstrap_components/static/bootstrap_components/temp.txt
bootstrap_components/templates/bootstrap_components/alert.html
bootstrap_components/templates/bootstrap_components/badge.html
bootstrap_components/templates/bootstrap_components/base.html
bootstrap_components/templates/bootstrap_components/breadcrumb.html
bootstrap_components/templates/bootstrap_components/card.html
bootstrap_components/templatetags/__init__.py
bootstrap_components/templatetags/util.py
bootstrap_components/tests/__init__.py
bootstrap_components/tests/settings.py
bootstrap_components/tests/test_render.py
bootstrap_components/tests/urls.py
dj_bootstrap_components.egg-info/PKG-INFO
dj_bootstrap_components.egg-info/SOURCES.txt
dj_bootstrap_components.egg-info/dependency_links.txt
dj_bootstrap_components.egg-info/top_level.txt
docs/Makefile
docs/make.bat
docs/source/alerts.md
docs/source/badges.md
docs/source/breadcrumbs.md
docs/source/cards.md
docs/source/components.md
docs/source/conf.py
docs/source/getting_started.md
docs/source/index.rst
docs/source/installing.md
docs/source/img/alerts.jpg
docs/source/img/badges.jpg
docs/source/img/breadcrumbs.jpg
docs/source/img/card-explainer.jpg