Metadata-Version: 1.1
Name: dj-bootstrap-components
Version: 0.2.2
Summary: A Django app that provides easy to use wrappers for common Bootstrap components
Home-page: https://github.com/IshanManchanda/dj-bootstrap-components
Author: Ishan Manchanda, Param Kapur
Author-email: kabootardevs@gmail.com
License: MIT
Download-URL: https://github.com/IshanManchanda/dj-bootstrap-components/releases
Platform: UNKNOWN
Classifier: Development Status :: 3 - Alpha
Classifier: Environment :: Web Environment
Classifier: Framework :: Django
Classifier: Framework :: Django :: 3.0
Classifier: Intended Audience :: Developers
Classifier: License :: OSI Approved :: MIT License
Classifier: Natural Language :: English
Classifier: Operating System :: OS Independent
Classifier: Programming Language :: Python
Classifier: Programming Language :: Python :: 3
Classifier: Programming Language :: Python :: 3 :: Only
Classifier: Programming Language :: Python :: 3.6
Classifier: Programming Language :: Python :: 3.7
Classifier: Programming Language :: Python :: 3.8
Classifier: Topic :: Internet :: WWW/HTTP
Classifier: Topic :: Internet :: WWW/HTTP :: Dynamic Content
